{
    "form": {
        "properties": {
            "sample_lvl": {
                "default": true,
                "description": "Calculate and report sample level statistics of TCR repertoire",
                "title": "Sample",
                "type": "boolean",
                "value": true
            },
            "compare_lvl": {
                "default": true,
                "description": "Comparative TCR repertoire analyses across samples and subjects",
                "title": "Compare",
                "type": "boolean",
                "value": true
            },
            "kmer_min_depth": {
                "default": "3",
                "description": "minimum depth of k-mer during clustering (GLIPH2)",
                "title": "kmer_min_depth",
                "type": "string"
            },
            "local_min_OVE": {
                "default": "10",
                "description": "local_min_OVE (GLIPH2)",
                "title": "local_min_OVE",
                "type": "string"
            },
            "local_min_pvalue": {
                "default": "0.001",
                "description": "minimum p-value for determining cluster significance (GLIPH2)",
                "title": "local_min_pvalue",
                "type": "string"
            },
            "p_depth": {
                "default": "1000",
                "description": "p_depth (GLIPH2)",
                "title": "p_depth",
                "type": "string"
            }
            
        }
    },
    "ui": {}
}